fakermaker/__init__.py
fakermaker/faker_maker.py
fakermaker-0.3.0.dist-info/LICENSE
fakermaker-0.3.0.dist-info/LICENSE.txt
fakermaker-0.3.0.dist-info/METADATA
fakermaker-0.3.0.dist-info/WHEEL
fakermaker-0.3.0.dist-info/top_level.txt
fakermaker-0.3.0.dist-info/RECORD
