Metadata-Version: 2.1
Name: fakermaker
Version: 0.3.0
Summary: Creates pandas dataframes containing fake data using a IPython magic function with custom domain specific language
Home-page: https://github.com/cassova/Faker-Maker
Author: Nicholas Miller
Author-email: miller.nicholas.a@gmail.com
License: MIT
Download-URL: https://github.com/cassova/Faker-Maker
Keywords: FakerMaker,faker,fake,data,generator,maker,creator,psuedo,random,test,sample
Platform: UNKNOWN
Requires-Dist: IPython
Requires-Dist: numpy
Requires-Dist: pandas
Requires-Dist: Faker
